pygwbl.py
pygwbl_pkg_Dagwbl-2.1.6.dist-info/LICENSE
pygwbl_pkg_Dagwbl-2.1.6.dist-info/METADATA
pygwbl_pkg_Dagwbl-2.1.6.dist-info/WHEEL
pygwbl_pkg_Dagwbl-2.1.6.dist-info/top_level.txt
pygwbl_pkg_Dagwbl-2.1.6.dist-info/RECORD
