Metadata-Version: 2.1
Name: pygwbl-pkg-Dagwbl
Version: 2.1.6
Summary: Dagwbl's personal tool set.
Home-page: https://github.com/Dagwbl/pygwbl
Author: Dagwbl
Author-email: Dagwbl@qq.com
License: UNKNOWN
Project-URL: Bug Tracker, https://github.com/Dagwbl/pygwbl/issues
Platform: UNKNOWN
Classifier: Programming Language :: Python :: 3
Classifier: License :: OSI Approved :: MIT License
Classifier: Operating System :: OS Independent
Requires-Python: >=3.6
License-File: LICENSE
